pyautocv/__init__.py
pyautocv/__main__.py
pyautocv/segmentation.py
pyautocv/version.py
pyautocv-0.3.1.dist-info/LICENSE
pyautocv-0.3.1.dist-info/METADATA
pyautocv-0.3.1.dist-info/WHEEL
pyautocv-0.3.1.dist-info/top_level.txt
pyautocv-0.3.1.dist-info/RECORD
