Metadata-Version: 2.1
Name: pyautocv
Version: 0.3.1
Summary: (Semi) Automated Image Processing
Home-page: http://www.github.com/Nelson-Gon/pyautocv
Author: Nelson Gonzabato
Author-email: gonzabato@hotmail.com
License: MIT
Download-URL: https://github.com/Nelson-Gon/pyautocv/archive/refs/tags/v0.3.1.zip
Keywords: image-data image-analysis computer-vision image-processing
Platform: UNKNOWN
Requires-Python: >=3.6
Requires-Dist: scikit-image
Requires-Dist: scipy
Requires-Dist: matplotlib
Requires-Dist: opencv-python
